<?xml version="1.0" encoding="utf-8"?>
<odoo>

    <data>
        <record id="account_payment_register_from_inherit" model="ir.ui.view">
            <field name="name">account.payment.register.from.inherit</field>
            <field name="model">account.payment.register</field>
            <field name="inherit_id" ref="account.view_account_payment_register_form"/>
            <field name="arch" type="xml">
                <group name="group3" position="replace">
                    <group name="group3" attrs="{'invisible': ['|', ('total_difference', '=', 0.0), '|', ('can_edit_wizard', '=', False), '&amp;', ('can_group_payments', '=', True), ('group_payment', '=', False)]}">
                        <field name="total_difference" />
                        <field name="global_tax_amount" readonly="1"/>
                        <label for="payment_difference"/>
                        <div>
                            <field name="payment_difference"/>
                            <field name="payment_difference_handling" widget="radio" nolabel="1"/>
                            <div attrs="{'invisible': [('payment_difference_handling','=','open')]}">
                                <label for="writeoff_account_id" string="Post Difference In" class="oe_edit_only"/>
                                <field name="writeoff_account_id" string="Post Difference In" options="{'no_create': True}" attrs="{'required': [('payment_difference_handling', '=', 'reconcile')]}"/>
                                <label for="writeoff_label" class="oe_edit_only" string="Label"/>
                                <field name="writeoff_label" attrs="{'required': [('payment_difference_handling', '=', 'reconcile')]}"/>
                            </div>
                        </div>
                    </group>
                </group>
            </field>
        </record>

    </data>


</odoo>
